LICENSE
README.md
setup.cfg
setup.py
iminstamastr/__init__.py
iminstamastr/main.py
iminstamastr.egg-info/PKG-INFO
iminstamastr.egg-info/SOURCES.txt
iminstamastr.egg-info/dependency_links.txt
iminstamastr.egg-info/requires.txt
iminstamastr.egg-info/top_level.txt