Metadata-Version: 2.1
Name: iminstamastr
Version: 0.2
Summary: Module for finding instagram user information.
Home-page: https://github.com/user/imtrollmastr
Download-URL: https://github.com/imtrollmastr/iminstamastr/archive/refs/tags/v_01.tar.gz
Author: Eddie STOCKTON
Author-email: eddiestockton420@gmail.com
License: MIT
Keywords: instagram,insta,finder,imtrollmastr,iminstamastr
Classifier: Development Status :: 3 - Alpha
Classifier: Intended Audience :: Developers
Classifier: Topic :: Software Development :: Build Tools
Classifier: License :: OSI Approved :: MIT License
Classifier: Programming Language :: Python :: 3
Classifier: Programming Language :: Python :: 3.4
Classifier: Programming Language :: Python :: 3.5
Classifier: Programming Language :: Python :: 3.6
License-File: LICENSE
